nameless/__init__.py
danilacasito_nameless-0.1.3.dist-info/METADATA
danilacasito_nameless-0.1.3.dist-info/WHEEL
danilacasito_nameless-0.1.3.dist-info/top_level.txt
danilacasito_nameless-0.1.3.dist-info/RECORD
