Metadata-Version: 2.1
Name: danilacasito-nameless
Version: 0.1.3
Summary: A python module for easily interacting with NamelessMC Forums
Author: danilacasito
Author-email: danilacasito8@gmail.com
License: MIT
